<?xml version="1.0" encoding="UTF-8"?>
<OAI-PMH xmlns="http://www.openarchives.org/OAI/2.0/" 
         xmlns:xsi="http://www.w3.org/2001/XMLSchema-instance"
         xsi:schemaLocation="http://www.openarchives.org/OAI/2.0/ http://www.openarchives.org/OAI/2.0/OAI-PMH.xsd">
    <responseDate>2026-07-13T06:21:34Z</responseDate>
                <request verb="GetRecord" identifier="oai:arXiv.org:2511.04028" metadataPrefix="arXiv">http://oaipmh.arxiv.org/oai</request>


    <GetRecord>
                <record>
                <header>
        <identifier>oai:arXiv.org:2511.04028</identifier>
        <datestamp>2025-11-10</datestamp>
            <setSpec>physics:quant-ph</setSpec>
    </header>

            <metadata>
                        <arXiv xmlns="http://arxiv.org/OAI/arXiv/" xmlns:xsi="http://www.w3.org/2001/XMLSchema-instance" xsi:schemaLocation="http://arxiv.org/OAI/arXiv/ https://oaipmh.arxiv.org/OAI/arXiv.xsd">
        <id>2511.04028</id>
        <created>2025-11-07</created>
            <updated>2025-11-10</updated>
        <authors>
                <author>
                    <keyname>Xue</keyname>
                        <forenames>Qing-Feng</forenames>
                </author>
                <author>
                    <keyname>Zhang</keyname>
                        <forenames>Qi</forenames>
                </author>
                <author>
                    <keyname>Zhuang</keyname>
                        <forenames>Xu-Cai</forenames>
                </author>
                <author>
                    <keyname>Xia</keyname>
                        <forenames>Yun-Jie</forenames>
                </author>
                <author>
                    <keyname>Russo</keyname>
                        <forenames>Enrico</forenames>
                </author>
                <author>
                    <keyname>Chiribella</keyname>
                        <forenames>Giulio</forenames>
                </author>
                <author>
                    <keyname>Franco</keyname>
                        <forenames>Rosario Lo</forenames>
                </author>
                <author>
                    <keyname>Man</keyname>
                        <forenames>Zhong-Xiao</forenames>
                </author>
        </authors>
        <title>Anomalous heat flow and quantum Otto cycle with indefinite causal order</title>
            <categories>quant-ph</categories>
            <comments>6 + 7 pages, 6 + 6 figures</comments>
            <license>http://arxiv.org/licenses/nonexclusive-distrib/1.0/</license>
            <abstract>The principle that heat spontaneously flows from higher temperature to lower temperature is a cornerstone of classical thermodynamics, often assumed to be independent of the sequence of interactions. While this holds true for macroscopic systems at equilibrium, here we show that, when the order of interactions between two identical thermalization channels is indefinite, an anomalous heat flow emerges, whereby heat can sometime flow from a colder entity to a hotter one. Taking advantage of this anomalous heat flow, we design a quantum Otto cycle with indefinite causal order, which not only achieves refrigeration but also generates work. The anomalous heat flow and the quantum Otto cycle are experimentally simulated in a photonic quantum setup, which provides a proof-of-principle demonstration of the theory.</abstract>
    </arXiv>

            </metadata>
        </record>

    </GetRecord>
</OAI-PMH>