<?xml version="1.0" encoding="UTF-8"?>
<OAI-PMH xmlns="http://www.openarchives.org/OAI/2.0/" 
         xmlns:xsi="http://www.w3.org/2001/XMLSchema-instance"
         xsi:schemaLocation="http://www.openarchives.org/OAI/2.0/ http://www.openarchives.org/OAI/2.0/OAI-PMH.xsd">
    <responseDate>2026-07-12T15:32:57Z</responseDate>
                <request verb="GetRecord" identifier="oai:arXiv.org:2506.01127v2" metadataPrefix="arXiv">http://oaipmh.arxiv.org/oai</request>


    <GetRecord>
                <record>
                <header>
        <identifier>oai:arXiv.org:2506.01127</identifier>
        <datestamp>2025-09-12</datestamp>
            <setSpec>physics:quant-ph</setSpec>
    </header>

            <metadata>
                        <arXiv xmlns="http://arxiv.org/OAI/arXiv/" xmlns:xsi="http://www.w3.org/2001/XMLSchema-instance" xsi:schemaLocation="http://arxiv.org/OAI/arXiv/ https://oaipmh.arxiv.org/OAI/arXiv.xsd">
        <id>2506.01127</id>
        <created>2025-08-26</created>
            <updated>2025-09-12</updated>
        <authors>
                <author>
                    <keyname>Wong</keyname>
                        <forenames>Yat</forenames>
                </author>
                <author>
                    <keyname>Jiang</keyname>
                        <forenames>Liang</forenames>
                </author>
        </authors>
        <title>Recycling Reflections for Perfect Photon Capture</title>
            <categories>quant-ph</categories>
            <doi>10.1103/ysnl-8krl</doi>
            <license>http://arxiv.org/licenses/nonexclusive-distrib/1.0/</license>
            <abstract>Efficient photon capture in optical cavities is essential for quantum networks and computing, yet single-pass methods suffer from uncaptured reflections due to finite capture windows and coupling strengths, precluding perfect transfer of arbitrary photonic states. We introduce a two-pass `pitch-and-catch&#39; method that recycles initial reflections to achieve perfect capture of arbitrary pulses in the noiseless regime and enhances fidelity under intrinsic losses. The method extends to photon emission, enabling arbitrary pulse shaping. This advance offers significant improvements for quantum repeaters, memories, and transduction, enhancing the toolkit for quantum information processing.</abstract>
    </arXiv>

            </metadata>
        </record>

    </GetRecord>
</OAI-PMH>