<?xml version="1.0" encoding="UTF-8"?>
<OAI-PMH xmlns="http://www.openarchives.org/OAI/2.0/" 
         xmlns:xsi="http://www.w3.org/2001/XMLSchema-instance"
         xsi:schemaLocation="http://www.openarchives.org/OAI/2.0/ http://www.openarchives.org/OAI/2.0/OAI-PMH.xsd">
    <responseDate>2026-07-13T00:29:14Z</responseDate>
                <request verb="GetRecord" identifier="oai:arXiv.org:2605.05122v1" metadataPrefix="arXiv">http://oaipmh.arxiv.org/oai</request>


    <GetRecord>
                <record>
                <header>
        <identifier>oai:arXiv.org:2605.05122</identifier>
        <datestamp>2026-05-08</datestamp>
            <setSpec>physics:astro-ph:CO</setSpec>
            <setSpec>physics:gr-qc</setSpec>
            <setSpec>physics:hep-ph</setSpec>
            <setSpec>physics:hep-th</setSpec>
    </header>

            <metadata>
                        <arXiv xmlns="http://arxiv.org/OAI/arXiv/" xmlns:xsi="http://www.w3.org/2001/XMLSchema-instance" xsi:schemaLocation="http://arxiv.org/OAI/arXiv/ https://oaipmh.arxiv.org/OAI/arXiv.xsd">
        <id>2605.05122</id>
        <created>2026-05-06</created>
            <updated>2026-05-08</updated>
        <authors>
                <author>
                    <keyname>Maki</keyname>
                        <forenames>Naoto</forenames>
                </author>
                <author>
                    <keyname>Kohri</keyname>
                        <forenames>Kazunori</forenames>
                </author>
        </authors>
        <title>Exponential Quintessence: Analytic Relationship Between the Current Equation of State Parameter and the Potential Parameter</title>
            <categories>astro-ph.CO gr-qc hep-ph hep-th</categories>
            <comments>19 pages, 6 figures, 1 table</comments>
            <report-no>KEK-TH-2832, KEK-Cosmo-0419</report-no>
            <license>http://arxiv.org/licenses/nonexclusive-distrib/1.0/</license>
            <abstract>Motivated by the indications of time-varying dark energy equation of state reported from DESI, we investigate a quintessence model with an exponential potential $V_0 e^{-λϕ/m_{\mathrm{pl}}}$. We derive an analytical relationship between the current equation of state parameter for the quintessence field and the potential parameter $λ$ required to realize sufficient duration of radiation and matter domination. Our results provide a useful analytical relation for inferring the potential parameter $λ$ from the observed current equation of state parameter. Furthermore, based on this framework, we provide a new analytical upper bound on the potential parameter $λ$ for current accelerated expansion. Concretely, we obtain $λ&lt;1.94$ by adopting $Ω_{\phi0}=0.685$.</abstract>
    </arXiv>

            </metadata>
        </record>

    </GetRecord>
</OAI-PMH>