<?xml version="1.0" encoding="UTF-8"?>
<OAI-PMH xmlns="http://www.openarchives.org/OAI/2.0/" 
         xmlns:xsi="http://www.w3.org/2001/XMLSchema-instance"
         xsi:schemaLocation="http://www.openarchives.org/OAI/2.0/ http://www.openarchives.org/OAI/2.0/OAI-PMH.xsd">
    <responseDate>2026-07-13T06:25:33Z</responseDate>
                <request verb="GetRecord" identifier="oai:arXiv.org:2511.02363" metadataPrefix="arXiv">http://oaipmh.arxiv.org/oai</request>


    <GetRecord>
                <record>
                <header>
        <identifier>oai:arXiv.org:2511.02363</identifier>
        <datestamp>2026-05-14</datestamp>
            <setSpec>physics:hep-ph</setSpec>
            <setSpec>physics:quant-ph</setSpec>
    </header>

            <metadata>
                        <arXiv xmlns="http://arxiv.org/OAI/arXiv/" xmlns:xsi="http://www.w3.org/2001/XMLSchema-instance" xsi:schemaLocation="http://arxiv.org/OAI/arXiv/ https://oaipmh.arxiv.org/OAI/arXiv.xsd">
        <id>2511.02363</id>
        <created>2026-05-13</created>
            <updated>2026-05-14</updated>
        <authors>
                <author>
                    <keyname>Sheng</keyname>
                        <forenames>Jie</forenames>
                </author>
                <author>
                    <keyname>Yanagida</keyname>
                        <forenames>Tsutomu T.</forenames>
                </author>
                <author>
                    <keyname>Gao</keyname>
                        <forenames>Bo</forenames>
                </author>
                <author>
                    <keyname>Ding</keyname>
                        <forenames>Hong</forenames>
                </author>
        </authors>
        <title>Testing Electromagnetic Memory via Acceleration-Induced Phase Imprints in Superconductors</title>
            <categories>hep-ph quant-ph</categories>
            <comments>8 pages, 3 figures</comments>
            <license>http://creativecommons.org/publicdomain/zero/1.0/</license>
            <abstract>Electromagnetic memory is an infrared observable of gauge theory associated with soft photons and large gauge transformations. Despite its fundamental theoretical importance, it has not yet been experimentally verified. From a phenomenological perspective, a transient electromagnetic configuration can leave a persistent gauge-invariant phase imprint on charged coherent states after the local field has vanished. We point out that the electric field and associated gauge potential induced inside a normal conductor by gravitational acceleration can provide a clean source for imprinting this phase, and it can then be read out through a superconducting protocol. For representative parameters, the predicted signal can lie within the range of present sensitivities, providing a possible tabletop route toward testing electromagnetic memory.</abstract>
    </arXiv>

            </metadata>
        </record>

    </GetRecord>
</OAI-PMH>