<?xml version="1.0" encoding="UTF-8"?>
<OAI-PMH xmlns="http://www.openarchives.org/OAI/2.0/" 
         xmlns:xsi="http://www.w3.org/2001/XMLSchema-instance"
         xsi:schemaLocation="http://www.openarchives.org/OAI/2.0/ http://www.openarchives.org/OAI/2.0/OAI-PMH.xsd">
    <responseDate>2026-07-13T06:27:35Z</responseDate>
                <request verb="GetRecord" identifier="oai:arXiv.org:2607.03560" metadataPrefix="arXiv">http://oaipmh.arxiv.org/oai</request>


    <GetRecord>
                <record>
                <header>
        <identifier>oai:arXiv.org:2607.03560</identifier>
        <datestamp>2026-07-07</datestamp>
            <setSpec>physics:gr-qc</setSpec>
            <setSpec>physics:astro-ph:CO</setSpec>
            <setSpec>physics:hep-ph</setSpec>
            <setSpec>physics:hep-th</setSpec>
    </header>

            <metadata>
                        <arXiv xmlns="http://arxiv.org/OAI/arXiv/" xmlns:xsi="http://www.w3.org/2001/XMLSchema-instance" xsi:schemaLocation="http://arxiv.org/OAI/arXiv/ https://oaipmh.arxiv.org/OAI/arXiv.xsd">
        <id>2607.03560</id>
        <created>2026-07-03</created>
            <updated>2026-07-07</updated>
        <authors>
                <author>
                    <keyname>Dvali</keyname>
                        <forenames>Gia</forenames>
                </author>
                <author>
                    <keyname>Zantedeschi</keyname>
                        <forenames>Michael</forenames>
                </author>
                <author>
                    <keyname>Zell</keyname>
                        <forenames>Sebastian</forenames>
                </author>
        </authors>
        <title>Black Hole Memory Burden and its Signatures in Gravitational Waves from Mergers</title>
            <categories>gr-qc astro-ph.CO hep-ph hep-th</categories>
            <comments>16 pages, 2 figures</comments>
            <license>http://creativecommons.org/licenses/by/4.0/</license>
            <abstract>Swift memory burden (MB) implies that the information stored in a black hole (BH) can modify its classical dynamics when the BH is perturbed. This influences the gravitational waves (GWs) emitted during BH mergers. In this paper, we investigate how the BH memory load is determined by the features of the collapsing source. We show that the memory load can vastly exceed the information content of its progenitor. An extreme example is a BH formed in a two-particle collision, which exhibits maximal MB. We then derive bounds for BHs formed through stellar collapse and examine the impact of swift MB on BH quasinormal modes, quantifying the MB-induced frequency shift of GWs. These findings imply that GW observations probe the fundamental mechanisms of BH information storage as well as their formation history.</abstract>
    </arXiv>

            </metadata>
        </record>

    </GetRecord>
</OAI-PMH>