<?xml version="1.0" encoding="UTF-8"?>
<OAI-PMH xmlns="http://www.openarchives.org/OAI/2.0/" 
         xmlns:xsi="http://www.w3.org/2001/XMLSchema-instance"
         xsi:schemaLocation="http://www.openarchives.org/OAI/2.0/ http://www.openarchives.org/OAI/2.0/OAI-PMH.xsd">
    <responseDate>2026-07-13T06:21:46Z</responseDate>
                <request verb="GetRecord" identifier="oai:arXiv.org:2601.02474" metadataPrefix="arXiv">http://oaipmh.arxiv.org/oai</request>


    <GetRecord>
                <record>
                <header>
        <identifier>oai:arXiv.org:2601.02474</identifier>
        <datestamp>2026-01-07</datestamp>
            <setSpec>physics:hep-ph</setSpec>
            <setSpec>physics:hep-ex</setSpec>
            <setSpec>physics:quant-ph</setSpec>
    </header>

            <metadata>
                        <arXiv xmlns="http://arxiv.org/OAI/arXiv/" xmlns:xsi="http://www.w3.org/2001/XMLSchema-instance" xsi:schemaLocation="http://arxiv.org/OAI/arXiv/ https://oaipmh.arxiv.org/OAI/arXiv.xsd">
        <id>2601.02474</id>
        <created>2026-01-05</created>
            <updated>2026-01-07</updated>
        <authors>
                <author>
                    <keyname>Hochberg</keyname>
                        <forenames>Yonit</forenames>
                </author>
                <author>
                    <keyname>Khalaf</keyname>
                        <forenames>Majed</forenames>
                </author>
                <author>
                    <keyname>Kurinsky</keyname>
                        <forenames>Noah</forenames>
                </author>
                <author>
                    <keyname>Lenoci</keyname>
                        <forenames>Alessandro</forenames>
                </author>
                <author>
                    <keyname>Ovadia</keyname>
                        <forenames>Rotem</forenames>
                </author>
        </authors>
        <title>Probing Dark Matter-Electron Interactions with Superconducting Qubits</title>
            <categories>hep-ph hep-ex quant-ph</categories>
            <comments>5 pages, 2 figures</comments>
            <license>http://arxiv.org/licenses/nonexclusive-distrib/1.0/</license>
            <abstract>Quantum device measurements are powerful tools to probe dark matter interactions. Among these, transmon qubits stand out for their ability to suppress external noise while remaining highly sensitive to tiny energy deposits. Ambient galactic halo dark matter interacting with electrons can deposit energy in the qubit, leading to changes in its decoherence time. Recent measurements of transmons have consistently measured, in various experimental setups, a residual contribution to the decoherence time unexplained by thermal noise or known external sources. We use such measurements to set the most stringent laboratory-based constraints to date on dark matter-electron scattering at the keV scale and competitive constraints on dark photon absorption.</abstract>
    </arXiv>

            </metadata>
        </record>

    </GetRecord>
</OAI-PMH>