<?xml version="1.0" encoding="UTF-8"?>
<OAI-PMH xmlns="http://www.openarchives.org/OAI/2.0/" 
         xmlns:xsi="http://www.w3.org/2001/XMLSchema-instance"
         xsi:schemaLocation="http://www.openarchives.org/OAI/2.0/ http://www.openarchives.org/OAI/2.0/OAI-PMH.xsd">
    <responseDate>2026-07-13T06:20:34Z</responseDate>
                <request verb="GetRecord" identifier="oai:arXiv.org:2510.21768" metadataPrefix="arXiv">http://oaipmh.arxiv.org/oai</request>


    <GetRecord>
                <record>
                <header>
        <identifier>oai:arXiv.org:2510.21768</identifier>
        <datestamp>2025-11-04</datestamp>
            <setSpec>physics:nucl-ex</setSpec>
            <setSpec>physics:cond-mat:supr-con</setSpec>
            <setSpec>physics:hep-ph</setSpec>
            <setSpec>physics:nucl-th</setSpec>
            <setSpec>physics:physics:ins-det</setSpec>
    </header>

            <metadata>
                        <arXiv xmlns="http://arxiv.org/OAI/arXiv/" xmlns:xsi="http://www.w3.org/2001/XMLSchema-instance" xsi:schemaLocation="http://arxiv.org/OAI/arXiv/ https://oaipmh.arxiv.org/OAI/arXiv.xsd">
        <id>2510.21768</id>
        <created>2025-10-16</created>
            <updated>2025-11-04</updated>
        <authors>
                <author>
                    <keyname>Prézeau</keyname>
                        <forenames>Gary</forenames>
                </author>
        </authors>
        <title>First non-zero measurement of a nuclear electric dipole moment</title>
            <categories>nucl-ex cond-mat.supr-con hep-ph nucl-th physics.ins-det</categories>
            <comments>42 pages, 82 figures</comments>
            <license>http://arxiv.org/licenses/nonexclusive-distrib/1.0/</license>
            <abstract>This paper reports the first non-zero measurement of a nuclear electric dipole moment using a novel method based on the rate of change of a supercurrent first proposed in 2016~\cite{https://doi.org/10.48550/arxiv.1604.02152} and fleshed out in this current paper. The theory, experimental concept and implementation are described in detail. The non-zero nuclear electric dipole moment measured with over 1000 hours of data was that of $^{181}$Ta producing a best value $|d_\text{e}^\text{Ta}|=(3.39\pm0.31_\text{stat})\cdot10^{-32}e\cdot\text{cm}$ and $|d_\text{e}^\text{Ta}|=(3.39\pm3.18)\cdot10^{-32}e\cdot\text{cm}&gt;0$ at 99.985\%CL. There is an uncertainty on the value of overall multiplicative parameters such as the self-inductance of the superconducting circuit ($\pm4\%$), the mutual inductance between the SQUID pickup coil and the sample wire ($\pm15\%$), and the magnitude of the solenoid current ($\pm5\%$). An upper-limit was estimated for the control element, $^{207}$Pb, $|d_\text{e}^\text{Pb}|\lesssim1.2\cdot10^{-31}e\cdot\text{cm}$ at 95\%CL.</abstract>
    </arXiv>

            </metadata>
        </record>

    </GetRecord>
</OAI-PMH>