<?xml version="1.0" encoding="UTF-8"?>
<OAI-PMH xmlns="http://www.openarchives.org/OAI/2.0/" 
         xmlns:xsi="http://www.w3.org/2001/XMLSchema-instance"
         xsi:schemaLocation="http://www.openarchives.org/OAI/2.0/ http://www.openarchives.org/OAI/2.0/OAI-PMH.xsd">
    <responseDate>2026-07-13T06:23:43Z</responseDate>
                <request verb="GetRecord" identifier="oai:arXiv.org:2602.05378" metadataPrefix="arXiv">http://oaipmh.arxiv.org/oai</request>


    <GetRecord>
                <record>
                <header>
        <identifier>oai:arXiv.org:2602.05378</identifier>
        <datestamp>2026-02-06</datestamp>
            <setSpec>physics:astro-ph:EP</setSpec>
    </header>

            <metadata>
                        <arXiv xmlns="http://arxiv.org/OAI/arXiv/" xmlns:xsi="http://www.w3.org/2001/XMLSchema-instance" xsi:schemaLocation="http://arxiv.org/OAI/arXiv/ https://oaipmh.arxiv.org/OAI/arXiv.xsd">
        <id>2602.05378</id>
        <created>2026-02-05</created>
            <updated>2026-02-06</updated>
        <authors>
                <author>
                    <keyname>Dahlbüdding</keyname>
                        <forenames>David</forenames>
                </author>
                <author>
                    <keyname>Grassi</keyname>
                        <forenames>Tommaso</forenames>
                </author>
                <author>
                    <keyname>Molaverdikhani</keyname>
                        <forenames>Karan</forenames>
                </author>
                <author>
                    <keyname>Roccetti</keyname>
                        <forenames>Giulia</forenames>
                </author>
                <author>
                    <keyname>Ercolano</keyname>
                        <forenames>Barbara</forenames>
                </author>
                <author>
                    <keyname>Braun</keyname>
                        <forenames>Dieter</forenames>
                </author>
                <author>
                    <keyname>Caselli</keyname>
                        <forenames>Paola</forenames>
                </author>
        </authors>
        <title>Habitability of Tidally Heated H$_2$-Dominated Exomoons around Free-Floating Planets</title>
            <categories>astro-ph.EP</categories>
            <comments>Accepted for publication in MNRAS</comments>
            <license>http://arxiv.org/licenses/nonexclusive-distrib/1.0/</license>
            <abstract>Exomoons around free-floating planets (FFPs) can survive their host planet&#39;s ejection. Such ejections can increase their orbital eccentricity, providing significant tidal heating in the absence of any stellar energy source. Previous studies suggested that liquid water could exist on such moons under thick CO$_2$-dominated atmospheres, but these models faced challenges with CO$_2$ condensation and atmospheric collapse, particularly in the high-pressure regimes that favoured long-term habitability. To address this, we employ a self-consistent model, including radiative transfer and equilibrium chemistry with condensation, to simulate a more stable hydrogen-dominated atmosphere for a range of initial chemical compositions, including C, O, and N. We find that such atmospheres can effectively trap heat via collision-induced absorption of H$_2$, maintaining surface temperatures suitable for liquid water for time-scales of up to 4.3 Gyr, depending on the surface pressure, while not prone to condensation-induced collapse. Wet-dry cycling caused by the strong tides together with the alkalinity of dissolved NH$_3$ could create favourable conditions for RNA polymerisation and thus support the emergence of life.</abstract>
    </arXiv>

            </metadata>
        </record>

    </GetRecord>
</OAI-PMH>